topsis/__init__.py
topsis_adityapandey_102217092-0.5.dist-info/LICENSE
topsis_adityapandey_102217092-0.5.dist-info/METADATA
topsis_adityapandey_102217092-0.5.dist-info/WHEEL
topsis_adityapandey_102217092-0.5.dist-info/top_level.txt
topsis_adityapandey_102217092-0.5.dist-info/RECORD
