Metadata-Version: 2.1
Name: topsis-adityapandey-102217092
Version: 0.5
Summary: A Python package for TOPSIS (Technique for Order of Preference by Similarity to Ideal Solution)
Home-page: https://github.com/asadityasonu/Topsiss-aditya-102217092
Author: Aditya Pandey
Author-email: asadityasonu@gmail.com
Project-URL: Bug Tracker, https://github.com/asadityasonu/Topsiss-aditya-102217092/issues
Project-URL: Documentation, https://github.com/asadityasonu/Topsiss-aditya-102217092
Project-URL: Source Code, https://github.com/asadityasonu/Topsiss-aditya-102217092
Keywords: topsis decision-making MCDM ranking
Classifier: Programming Language :: Python :: 3
Classifier: License :: OSI Approved :: MIT License
Classifier: Operating System :: OS Independent
Classifier: Intended Audience :: Developers
Classifier: Topic :: Scientific/Engineering :: Information Analysis
Requires-Python: >=3.6
License-File: LICENSE
Requires-Dist: numpy
Requires-Dist: pandas
